pydantic_i18n/__init__.py
pydantic_i18n/loaders.py
pydantic_i18n/main.py
pydantic_i18n/py.typed
pydantic_i18n-0.4.4.dist-info/LICENSE
pydantic_i18n-0.4.4.dist-info/WHEEL
pydantic_i18n-0.4.4.dist-info/METADATA
pydantic_i18n-0.4.4.dist-info/RECORD
